hunspell/hunspell.cpp
hunspell/libhunspell-1.7.so.0
hunspell/_version.py
hunspell/thread.hpp
hunspell/platform.py
hunspell/hunspell.cpython-310-x86_64-linux-gnu.so
hunspell/hunspell.pyx
hunspell/hunspell.pxd
hunspell/thread.pxd
hunspell/__init__.py
hunspell/dictionaries/en_GB.aff
hunspell/dictionaries/en_CA.dic
hunspell/dictionaries/en_ZA.dic
hunspell/dictionaries/en_AU.aff
hunspell/dictionaries/en_US.dic
hunspell/dictionaries/a.dic
hunspell/dictionaries/en_AU.dic
hunspell/dictionaries/en_NZ.dic
hunspell/dictionaries/en_US.aff
hunspell/dictionaries/en_ZA.aff
hunspell/dictionaries/en_CA.aff
hunspell/dictionaries/test.aff
hunspell/dictionaries/test.dic
hunspell/dictionaries/en_GB.dic
hunspell/dictionaries/en_NZ.aff
cyhunspell_py310-2.0.3.dist-info/RECORD
cyhunspell_py310-2.0.3.dist-info/top_level.txt
cyhunspell_py310-2.0.3.dist-info/LICENSE
cyhunspell_py310-2.0.3.dist-info/METADATA
cyhunspell_py310-2.0.3.dist-info/WHEEL
