Metadata-Version: 2.1
Name: cyhunspell-py310
Version: 2.0.3
Summary: A wrapper on hunspell for use in Python
Home-page: https://github.com/MSeal/cython_hunspell
Download-URL: https://github.com/MSeal/cython_hunspell/tarball/v2.0.3
Author: Matthew Seal
Author-email: mseal007@gmail.com
License: MIT + MPL 1.1/GPL 2.0/LGPL 2.1
Keywords: hunspell,spelling,correction
Classifier: Development Status :: 5 - Production/Stable
Classifier: Topic :: Utilities
Classifier: License :: OSI Approved :: MIT License
Classifier: Natural Language :: English
Classifier: Programming Language :: Python :: 3
License-File: LICENSE
Requires-Dist: cacheman (>=2.0.6)
Provides-Extra: dev
Requires-Dist: cython (==0.29.21) ; extra == 'dev'
Requires-Dist: wheel ; extra == 'dev'
Requires-Dist: twine ; extra == 'dev'
Provides-Extra: test
Requires-Dist: pytest ; extra == 'test'
